__init__.py
BayesMCDM/__init__.py
BayesMCDM/Alternative/__init__.py
BayesMCDM/Alternative/alternative.py
BayesMCDM/Models/MCDMProblem.py
BayesMCDM/Models/__init__.py
BayesMCDM/Models/AHP/GaussianAHP.py
BayesMCDM/Models/AHP/IntervalAHP.py
BayesMCDM/Models/AHP/StandardAHP.py
BayesMCDM/Models/AHP/TriangularAHP.py
BayesMCDM/Models/AHP/__init__.py
BayesMCDM/Models/BWM/BetaBWM.py
BayesMCDM/Models/BWM/GaussianBWM.py
BayesMCDM/Models/BWM/IntervalBWM.py
BayesMCDM/Models/BWM/MultinomialBWM.py
BayesMCDM/Models/BWM/StandardBWM.py
BayesMCDM/Models/BWM/TriangularBWM.py
BayesMCDM/Models/BWM/__init__.py
BayesMCDM/Models/PointAllocation/GaussianPointAllocation.py
BayesMCDM/Models/PointAllocation/IntervalPointAllocation.py
BayesMCDM/Models/PointAllocation/StandardPointAllocation.py
BayesMCDM/Models/PointAllocation/TriangularPointAllocation.py
BayesMCDM/Models/PointAllocation/__init__.py
BayesMCDM/Models/SWING/GaussianSWING.py
BayesMCDM/Models/SWING/IntervalSWING.py
BayesMCDM/Models/SWING/StandardSWING.py
BayesMCDM/Models/SWING/TriangularSWING.py
BayesMCDM/Models/SWING/__init__.py
BayesMCDM/Models/WeightAnalyzer/IntervalWeightAnalyzer.py
BayesMCDM/Models/WeightAnalyzer/StandardWeightAnalyzer.py
BayesMCDM/Models/WeightAnalyzer/__init__.py
BayesMCDM/Visualizer/ClusterVisualizer.py
BayesMCDM/Visualizer/CredalRanking.py
BayesMCDM/Visualizer/WeightVisualizer.py
BayesMCDM/Visualizer/__init__.py
bayesmcdm-0.1.1.59.dist-info/METADATA
bayesmcdm-0.1.1.59.dist-info/WHEEL
bayesmcdm-0.1.1.59.dist-info/top_level.txt
bayesmcdm-0.1.1.59.dist-info/RECORD
