Metadata-Version: 2.4
Name: BayesMCDM
Version: 0.1.1.59
Summary: Bayesian Multi-Criteria Decision-Making Toolkit
Author: Majid Mohammadi
Maintainer-email: Majid Mohammadi <majid.mohammadi690@gmail.com>
License: MIT
Keywords: python,Multi Criteria Decision Making (MCDM),Bayesian,credal ranking,Analytic Hierarchy Process (AHP),Best Worst Method (BWM),SWING,Point Allocation,Weight Aggregation,Bayesian Inference,Decision Analysis,Decision Support Systems,Decision Making,Group Decision Making,Group aggregation,group clustering,Interval preferences,Preference modeling,Preference aggregation,Preference elicitation,Gaussian number preferences,Triangular number preferences,Interval number preferences,Fuzzy number p
Requires-Python: >=3.9
Requires-Dist: numpy
Requires-Dist: pystan
Requires-Dist: graphviz==0.17
Requires-Dist: ipython
Requires-Dist: matplotlib
Requires-Dist: nest_asyncio
Requires-Dist: pandas
Requires-Dist: scipy
Requires-Dist: seaborn
Requires-Dist: setuptools
Requires-Dist: networkx
